lightRaven/__init__.py
lightRaven/__version__.py
lightRaven/agent/__init__.py
lightRaven/agent/cem.py
lightRaven/agent/cem_seldonian.py
lightRaven/func/__init__.py
lightRaven/func/ci.py
lightRaven/func/ci_jitfree.py
lightRaven/policy/__init__.py
lightRaven/policy/policy.py
lightRaven/sampling/__init__.py
lightRaven/sampling/base.py
lightRaven/sampling/cwpdis.py
lightRaven/sampling/imptsamp.py
lightRaven/sampling/pdis.py
lightRaven/sampling/wis.py
lightRaven/utils/__init__.py
lightRaven/utils/data_gen.py
lightRaven/utils/safety_test.py
lightRaven-0.1.0.dist-info/LICENSE
lightRaven-0.1.0.dist-info/METADATA
lightRaven-0.1.0.dist-info/WHEEL
lightRaven-0.1.0.dist-info/top_level.txt
lightRaven-0.1.0.dist-info/RECORD
