Metadata-Version: 2.1
Name: lightRaven
Version: 0.1.0
Summary: Library for Fast Offline RL Analysis with Minimum Dependencies
Home-page: https://github.com/M0gician/lightRaven
Author: Tommy Yang (m0g1cian)
Author-email: tommyyang0524@gmail.com
License: MIT
Platform: UNKNOWN
Classifier: License :: OSI Approved :: MIT License
Classifier: Programming Language :: Python
Classifier: Programming Language :: Python :: 3
Classifier: Programming Language :: Python :: 3.7
Classifier: Programming Language :: Python :: Implementation :: CPython
Requires-Python: >=3.7.0
Requires-Dist: numpy
Requires-Dist: scipy
Requires-Dist: numba
Requires-Dist: gym
